uvpool/__init__.py
uvpool-0.1.1.dist-info/WHEEL
uvpool-0.1.1.dist-info/METADATA
uvpool-0.1.1.dist-info/RECORD
